sattrack/__init__.py
sattrack/api.py
sattrack/config.py
sattrack/bodies/__init__.py
sattrack/bodies/_tables.py
sattrack/bodies/api.py
sattrack/bodies/body.py
sattrack/bodies/earth.py
sattrack/bodies/exceptions.py
sattrack/bodies/moon.py
sattrack/bodies/position.py
sattrack/bodies/sun.py
sattrack/bodies/topocentric.py
sattrack/core/__init__.py
sattrack/core/_analysis.py
sattrack/core/api.py
sattrack/core/coordinates.py
sattrack/core/exceptions.py
sattrack/core/juliandate.py
sattrack/orbit/__init__.py
sattrack/orbit/api.py
sattrack/orbit/elements.py
sattrack/orbit/exceptions.py
sattrack/orbit/orbitpath.py
sattrack/orbit/satellite.py
sattrack/orbit/sgp4.cp311-win_amd64.pyd
sattrack/orbit/tle.py
sattrack/satellitepass/__init__.py
sattrack/satellitepass/api.py
sattrack/satellitepass/eclipse.py
sattrack/satellitepass/exceptions.py
sattrack/satellitepass/info.py
sattrack/satellitepass/satpass.py
sattrack/util/__init__.py
sattrack/util/api.py
sattrack/util/constants.py
sattrack/util/helpers.py
sattrack-0.4.1.dist-info/LICENSE.txt
sattrack-0.4.1.dist-info/METADATA
sattrack-0.4.1.dist-info/WHEEL
sattrack-0.4.1.dist-info/top_level.txt
sattrack-0.4.1.dist-info/RECORD
