Metadata-Version: 2.1
Name: sattrack
Version: 0.4.1
Summary: Compute positioning and angle data for satellites in orbit.
Author-email: Quinton Barnes <devqbizzle68@gmail.com>
Project-URL: Homepage, https://github.com/qbizzle68/sattrack
Project-URL: Bug Tracker, https://github.com/qbizzle68/sattrack/issues
Classifier: Development Status :: 3 - Alpha
Classifier: Environment :: Console
Classifier: Intended Audience :: Science/Research
Classifier: License :: OSI Approved :: MIT License
Classifier: Programming Language :: Python :: 3
Classifier: Topic :: Scientific/Engineering
Classifier: Topic :: Scientific/Engineering :: Astronomy
Requires-Python: >=3.8
License-File: LICENSE.txt
Requires-Dist: pyevspace
Requires-Dist: requests
